ioka_python/__init__.py
ioka_python/api_resources/__init__.py
ioka_python/api_resources/abstract/api_resource.py
ioka_python/api_resources/customer.py
ioka_python/api_resources/dashboard.py
ioka_python/api_resources/order.py
ioka_python/api_resources/payment.py
ioka_python-0.1.1.dist-info/METADATA
ioka_python-0.1.1.dist-info/WHEEL
ioka_python-0.1.1.dist-info/RECORD
