Metadata-Version: 2.1
Name: ioka-python
Version: 0.1.1
Summary: 
Author: Aldiyar Dabarov
Author-email: dabarov.aldiyar@gmail.com
Requires-Python: >=3.10,<4.0
Classifier: Programming Language :: Python :: 3
Classifier: Programming Language :: Python :: 3.10
Classifier: Programming Language :: Python :: 3.11
Requires-Dist: requests (>=2.28.2,<3.0.0)
